setup.py
urwid_geventloop.py
urwid_geventloop.egg-info/PKG-INFO
urwid_geventloop.egg-info/SOURCES.txt
urwid_geventloop.egg-info/dependency_links.txt
urwid_geventloop.egg-info/requires.txt
urwid_geventloop.egg-info/top_level.txt