Metadata-Version: 1.1
Name: urwid-geventloop
Version: 0.0.0.dev
Summary: Event loop based on gevent
Home-page: https://github.com/what-studio/urwid-geventloop
Author: What! Studio
Author-email: sub@nexon.co.kr
License: BSD
Platform: any
Classifier: Development Status :: 2 - Pre-Alpha
Classifier: Intended Audience :: Developers
Classifier: License :: Public Domain
Classifier: Operating System :: MacOS :: MacOS X
Classifier: Operating System :: POSIX
Classifier: Operating System :: Unix
Classifier: Programming Language :: Python
Classifier: Programming Language :: Python :: 2.7
Classifier: Programming Language :: Python :: Implementation :: CPython
Classifier: Topic :: Internet
Classifier: Topic :: Software Development :: Libraries :: Python Modules
